{
    "data": [
        {
            "question": " What is the capital city of Australia?",
            "option": [
                "Sydney",
                "Melbourne",
                "Canberra",
                "Brisbane"
            ],
            "answer":"Canberra"
        },
        {
            "question": " What is the chemical symbol for gold?",
            "option": [
                "Au",
                "Ag",
                "Gd",
                "Gi"
            ],
            "answer":"Au"
        },
        {
            "question": " In which year did Christopher Columbus first reach the Americas?",
            "option": [
                "1492",
                "1588",
                "1422",
                "1517"
            ],
            "answer":"1492"
        },
        {
            "question": " Who wrote the novel 'To Kill a Mockingbird'?",
            "option": [
                "Ernest Hemingway",
                "Harper Lee",
                "J.D. Salinger",
                "F. Scott Fitzgerald"
            ],
            "answer":"Harper Lee"
        }
    
    ]
}